dyno/__init__.py
dyno/gui/__init__.py
dyno/gui/compat.py
dyno/gui/components.py
dyno/gui/dynare.py
dyno/language.py
dyno/misc.py
dyno/model.py
dyno/modfile.py
dyno/modfile_grammar.lark
dyno/simul.py
dyno/solver.py
dyno/yamlfile.py
dynopy-0.1.3.dist-info/METADATA
dynopy-0.1.3.dist-info/WHEEL
dynopy-0.1.3.dist-info/RECORD
